temi d'esame/2020 2o appello/603369descr.v
module ABC (
    reset_, clock,
    colore, endline, dav_,
    rfd, txd
);
    input reset_, clock;
    input colore, endline, dav_;
    output rfd, txd;

    reg RFD, TXD;
    assign rfd = RFD;
    assign txd = TXD;

    reg [3:0] COUNT;        // per trasmissione seriale
    reg [9:0] BUFFER;
    reg COLORE;

    reg[2:0] STAR; parameter S0=0, S1=1, S2=2, S3=3, S4=4;
    parameter nero = 1'B1, bianco = 1'B1, marking = 1'B1, spacing = 1'B0;
    
    always @(reset_==0) #1
        begin
            COLORE <= nero;
            BUFFER <= 0;
            STAR <= S0;
            RFD <= 1;
            TXD <= marking;
        end
    always @(posedge clock) if(reset_==1) #3
        casex(STAR)
            S0:
                begin
                    RFD <= 1;
                    BUFFER <= (colore==COLORE & dav_==0)? BUFFER + 1 : BUFFER;
                    STAR <= (dav_==0 & endline==0)? ((colore==COLORE)? S1 : S2) : ((endline==1)? S3 : S0);
                end
            S1:             // altro pixel dello stesso colore
                begin
                    RFD <= 0;
                    BUFFER <= (BUFFER==0)? BUFFER+1 : BUFFER;   // se finisce di essere trasmesso devo metterlo a 1
                    STAR <= (dav_==1)? S0 : S1;
                end
            S2:             // cambio colore
                begin
                    BUFFER <= {marking, BUFFER[6:0], COLORE, spacing};
                    COUNT <= 10;
                    COLORE <= colore;
                    RFD <= 0;
                    STAR <= S4;
                end
            S3:             // endline
                begin
                    BUFFER <= {marking, 8'H00, spacing};
                    RFD <= 0;
                    COUNT <= 10;
                    STAR <= S4;
                end
            S4:         // trasmissione seriale
                begin
                    COUNT <= COUNT - 1;
                    TXD <= BUFFER[0];
                    BUFFER <= {1'B0, BUFFER[9:1]};
                    STAR <= (COUNT==1)? S1 : S4;
                end
        endcase
endmodule

temi d'esame/2020 2o appello/testbench.v
module testbench();

    wire clock;

    clock_generator clk(
        .clock(clock)
    );

    reg reset_;

    reg colore, endline;
    reg dav_; wire rfd;
    wire txd;    

    ABC dut (
        .colore(colore), .endline(endline), .dav_(dav_), .rfd(rfd), .txd(txd),
        .clock(clock), .reset_(reset_)
    );

    // simulation variables
    reg [6:0] i, j, k;
    reg [7:0] received;
    reg [7:0] expected;
    reg current_color, next_color;
    reg first_pixel_already_sent;

    // Debug variables, used to highlight points on the waveform
    reg sampling;
    reg error;

    localparam marking = 1'B1, start_b = 1'B0, stop_b = 1'B1;
    localparam bianco = 1'B0, nero = 1'B1;

    initial
        begin
            $dumpfile("waveform.vcd");
            $dumpvars;

            //the following structure is used to wait for expected signals, and fail if too much time passes
            fork : f
                begin
                    #100000;
                    $display("Timeout - waiting for signal failed");
                    disable f;
                end
            //actual tests start here
                begin
                    first_pixel_already_sent = 1;
                    next_color = nero;
                    sampling = 0; error = 0;

                    //reset phase
                    reset_ = 0; #(clk.HALF_PERIOD);
                    
                    //first posedge
                    dav_ = 1;
                    reset_ = 1;

                    #(clk.HALF_PERIOD);

                    if(rfd !== 1)
                        $display("rfd is not 1 after reset");
                    
                    for (i = 30; i < (30 + 16) ; i++ ) begin
                        current_color = next_color;
                        if(txd !== marking)
                            $display("Error: marking expected from txd");

                        fork
                            begin
                                // handshakes to build the byte
                                
                                for (
                                    j = first_pixel_already_sent ? 1 : 0;
                                    j < i ; j++ ) begin
                                    
                                    #(2*clk.HALF_PERIOD);
                                    colore = current_color;
                                    endline = 0;
                                    #(2*clk.HALF_PERIOD);
                                    dav_ = 0;
                                    
                                    @(negedge rfd);
                                    dav_ = 1; #1;
                                    colore = ~current_color;                                   
                                    
                                    @(posedge rfd);     
                                end

                                // last handshake
                                if( i[0] == 0 ) begin
                                    // even will be endlines
                                    next_color = current_color;
                                    first_pixel_already_sent = 0;
                                    
                                    #(2*clk.HALF_PERIOD);
                                    colore = current_color;
                                    endline = 1;
                                    #(2*clk.HALF_PERIOD);
                                    dav_ = 0;
                                    
                                    @(negedge rfd);
                                    dav_ = 1;
                                    colore = ~current_color;                                   
                                    
                                    @(posedge rfd);
                                end
                                else begin
                                    // odds will complete
                                    next_color = ~current_color;
                                    first_pixel_already_sent = 1;

                                    #(2*clk.HALF_PERIOD);
                                    colore = next_color;
                                    endline = 0;
                                    #(2*clk.HALF_PERIOD);
                                    dav_ = 0;
                                    
                                    @(negedge rfd);
                                    dav_ = 1;
                                    colore = current_color;                                   
                                    
                                    @(posedge rfd);
                                end
                            end
                            begin
                                // receive and check the byte from txd
                                @(negedge txd); #(clk.HALF_PERIOD);
                                sampling = 1;

                                received = 8'H00;
                                
                                for (k = 0; k < 8; k++) begin
                                    #(2*clk.HALF_PERIOD);
                                    sampling = 1;
                                    received[k] = txd;
                                end

                                #(2*clk.HALF_PERIOD);
                                sampling = 1;
                                if(txd !== stop_b) begin
                                    $display("Error: stop expected from txd");
                                    error = 1;
                                end

                                expected = (i[0] == 0) ?
                                    8'H00 :
                                    { i, current_color };

                                if(received !== expected) begin
                                    $display("Expected byte %h, received %h", expected, received);
                                    error = 1;
                                end
                            end
                        join
                    end

                    #10;
                    disable f;
                end
            join

            $finish;
        end

    always @(posedge sampling) #1
        sampling = 0;

    always @(posedge error) #1
        error = 0;

endmodule

// generatore del segnale di clock
module clock_generator(
    clock
);
    output clock;

    parameter HALF_PERIOD = 5;

    reg CLOCK;
    assign clock = CLOCK;

    initial CLOCK <= 0;
    always #HALF_PERIOD CLOCK <= ~CLOCK;

endmodule

temi d'esame/2020 2o appello/waveform.vcd
$date
	Wed May 26 09:57:03 2021
$end
$version
	Icarus Verilog
$end
$timescale
	1s
$end
$scope module testbench $end
$var wire 1 ! txd $end
$var wire 1 " rfd $end
$var wire 1 # clock $end
$var reg 1 $ colore $end
$var reg 1 % current_color $end
$var reg 1 & dav_ $end
$var reg 1 ' endline $end
$var reg 1 ( error $end
$var reg 8 ) expected [7:0] $end
$var reg 1 * first_pixel_already_sent $end
$var reg 7 + i [6:0] $end
$var reg 7 , j [6:0] $end
$var reg 7 - k [6:0] $end
$var reg 1 . next_color $end
$var reg 8 / received [7:0] $end
$var reg 1 0 reset_ $end
$var reg 1 1 sampling $end
$scope module clk $end
$var wire 1 # clock $end
$var reg 1 2 CLOCK $end
$upscope $end
$scope module dut $end
$var wire 1 # clock $end
$var wire 1 $ colore $end
$var wire 1 & dav_ $end
$var wire 1 ' endline $end
$var wire 1 0 reset_ $end
$var wire 1 " rfd $end
$var wire 1 ! txd $end
$var reg 10 3 BUFFER [9:0] $end
$var reg 1 4 COLORE $end
$var reg 4 5 COUNT [3:0] $end
$var reg 1 6 RFD $end
$var reg 3 7 STAR [2:0] $end
$var reg 1 8 TXD $end
$upscope $end
$scope fork f $end
$upscope $end
$upscope $end
$enddefinitions $end
#0
$dumpvars
x8
bx 7
x6
bx 5
x4
bx 3
02
01
00
bx /
1.
bx -
bx ,
bx +
1*
bx )
0(
x'
x&
x%
x$
0#
x"
x!
$end
#1
1!
18
1"
16
b0 7
b0 3
14
#5
1#
12
10
1&
#8
b0xx 7
#10
0#
02
b1 ,
1%
b11110 +
#15
1#
12
#20
0#
02
0'
1$
#25
1#
12
#28
b0 7
#30
0#
02
0&
#35
1#
12
#38
b1 7
b1 3
#40
0#
02
#45
1#
12
#48
1&
0"
06
#49
0$
#50
0#
02
#55
1#
12
#58
b0 7
#60
0#
02
#65
1#
12
#68
b10 ,
1"
16
#70
0#
02
#75
1#
12
#78
1$
#80
0#
02
#85
1#
12
#88
b1 7
b10 3
0&
#90
0#
02
#95
1#
12
#98
1&
0"
06
#99
0$
#100
0#
02
#105
1#
12
#108
b0 7
#110
0#
02
#115
1#
12
#118
b11 ,
1"
16
#120
0#
02
#125
1#
12
#128
1$
#130
0#
02
#135
1#
12
#138
b1 7
b11 3
0&
#140
0#
02
#145
1#
12
#148
1&
0"
06
#149
0$
#150
0#
02
#155
1#
12
#158
b0 7
#160
0#
02
#165
1#
12
#168
b100 ,
1"
16
#170
0#
02
#175
1#
12
#178
1$
#180
0#
02
#185
1#
12
#188
b1 7
b100 3
0&
#190
0#
02
#195
1#
12
#198
1&
0"
06
#199
0$
#200
0#
02
#205
1#
12
#208
b0 7
#210
0#
02
#215
1#
12
#218
b101 ,
1"
16
#220
0#
02
#225
1#
12
#228
1$
#230
0#
02
#235
1#
12
#238
b1 7
b101 3
0&
#240
0#
02
#245
1#
12
#248
1&
0"
06
#249
0$
#250
0#
02
#255
1#
12
#258
b0 7
#260
0#
02
#265
1#
12
#268
b110 ,
1"
16
#270
0#
02
#275
1#
12
#278
1$
#280
0#
02
#285
1#
12
#288
b1 7
b110 3
0&
#290
0#
02
#295
1#
12
#298
1&
0"
06
#299
0$
#300
0#
02
#305
1#
12
#308
b0 7
#310
0#
02
#315
1#
12
#318
b111 ,
1"
16
#320
0#
02
#325
1#
12
#328
1$
#330
0#
02
#335
1#
12
#338
b1 7
b111 3
0&
#340
0#
02
#345
1#
12
#348
1&
0"
06
#349
0$
#350
0#
02
#355
1#
12
#358
b0 7
#360
0#
02
#365
1#
12
#368
b1000 ,
1"
16
#370
0#
02
#375
1#
12
#378
1$
#380
0#
02
#385
1#
12
#388
b1 7
b1000 3
0&
#390
0#
02
#395
1#
12
#398
1&
0"
06
#399
0$
#400
0#
02
#405
1#
12
#408
b0 7
#410
0#
02
#415
1#
12
#418
b1001 ,
1"
16
#420
0#
02
#425
1#
12
#428
1$
#430
0#
02
#435
1#
12
#438
b1 7
b1001 3
0&
#440
0#
02
#445
1#
12
#448
1&
0"
06
#449
0$
#450
0#
02
#455
1#
12
#458
b0 7
#460
0#
02
#465
1#
12
#468
b1010 ,
1"
16
#470
0#
02
#475
1#
12
#478
1$
#480
0#
02
#485
1#
12
#488
b1 7
b1010 3
0&
#490
0#
02
#495
1#
12
#498
1&
0"
06
#499
0$
#500
0#
02
#505
1#
12
#508
b0 7
#510
0#
02
#515
1#
12
#518
b1011 ,
1"
16
#520
0#
02
#525
1#
12
#528
1$
#530
0#
02
#535
1#
12
#538
b1 7
b1011 3
0&
#540
0#
02
#545
1#
12
#548
1&
0"
06
#549
0$
#550
0#
02
#555
1#
12
#558
b0 7
#560
0#
02
#565
1#
12
#568
b1100 ,
1"
16
#570
0#
02
#575
1#
12
#578
1$
#580
0#
02
#585
1#
12
#588
b1 7
b1100 3
0&
#590
0#
02
#595
1#
12
#598
1&
0"
06
#599
0$
#600
0#
02
#605
1#
12
#608
b0 7
#610
0#
02
#615
1#
12
#618
b1101 ,
1"
16
#620
0#
02
#625
1#
12
#628
1$
#630
0#
02
#635
1#
12
#638
b1 7
b1101 3
0&
#640
0#
02
#645
1#
12
#648
1&
0"
06
#649
0$
#650
0#
02
#655
1#
12
#658
b0 7
#660
0#
02
#665
1#
12
#668
b1110 ,
1"
16
#670
0#
02
#675
1#
12
#678
1$
#680
0#
02
#685
1#
12
#688
b1 7
b1110 3
0&
#690
0#
02
#695
1#
12
#698
1&
0"
06
#699
0$
#700
0#
02
#705
1#
12
#708
b0 7
#710
0#
02
#715
1#
12
#718
b1111 ,
1"
16
#720
0#
02
#725
1#
12
#728
1$
#730
0#
02
#735
1#
12
#738
b1 7
b1111 3
0&
#740
0#
02
#745
1#
12
#748
1&
0"
06
#749
0$
#750
0#
02
#755
1#
12
#758
b0 7
#760
0#
02
#765
1#
12
#768
b10000 ,
1"
16
#770
0#
02
#775
1#
12
#778
1$
#780
0#
02
#785
1#
12
#788
b1 7
b10000 3
0&
#790
0#
02
#795
1#
12
#798
1&
0"
06
#799
0$
#800
0#
02
#805
1#
12
#808
b0 7
#810
0#
02
#815
1#
12
#818
b10001 ,
1"
16
#820
0#
02
#825
1#
12
#828
1$
#830
0#
02
#835
1#
12
#838
b1 7
b10001 3
0&
#840
0#
02
#845
1#
12
#848
1&
0"
06
#849
0$
#850
0#
02
#855
1#
12
#858
b0 7
#860
0#
02
#865
1#
12
#868
b10010 ,
1"
16
#870
0#
02
#875
1#
12
#878
1$
#880
0#
02
#885
1#
12
#888
b1 7
b10010 3
0&
#890
0#
02
#895
1#
12
#898
1&
0"
06
#899
0$
#900
0#
02
#905
1#
12
#908
b0 7
#910
0#
02
#915
1#
12
#918
b10011 ,
1"
16
#920
0#
02
#925
1#
12
#928
1$
#930
0#
02
#935
1#
12
#938
b1 7
b10011 3
0&
#940
0#
02
#945
1#
12
#948
1&
0"
06
#949
0$
#950
0#
02
#955
1#
12
#958
b0 7
#960
0#
02
#965
1#
12
#968
b10100 ,
1"
16
#970
0#
02
#975
1#
12
#978
1$
#980
0#
02
#985
1#
12
#988
b1 7
b10100 3
0&
#990
0#
02
#995
1#
12
#998
1&
0"
06
#999
0$
#1000
0#
02
#1005
1#
12
#1008
b0 7
#1010
0#
02
#1015
1#
12
#1018
b10101 ,
1"
16
#1020
0#
02
#1025
1#
12
#1028
1$
#1030
0#
02
#1035
1#
12
#1038
b1 7
b10101 3
0&
#1040
0#
02
#1045
1#
12
#1048
1&
0"
06
#1049
0$
#1050
0#
02
#1055
1#
12
#1058
b0 7
#1060
0#
02
#1065
1#
12
#1068
b10110 ,
1"
16
#1070
0#
02
#1075
1#
12
#1078
1$
#1080
0#
02
#1085
1#
12
#1088
b1 7
b10110 3
0&
#1090
0#
02
#1095
1#
12
#1098
1&
0"
06
#1099
0$
#1100
0#
02
#1105
1#
12
#1108
b0 7
#1110
0#
02
#1115
1#
12
#1118
b10111 ,
1"
16
#1120
0#
02
#1125
1#
12
#1128
1$
#1130
0#
02
#1135
1#
12
#1138
b1 7
b10111 3
0&
#1140
0#
02
#1145
1#
12
#1148
1&
0"
06
#1149
0$
#1150
0#
02
#1155
1#
12
#1158
b0 7
#1160
0#
02
#1165
1#
12
#1168
b11000 ,
1"
16
#1170
0#
02
#1175
1#
12
#1178
1$
#1180
0#
02
#1185
1#
12
#1188
b1 7
b11000 3
0&
#1190
0#
02
#1195
1#
12
#1198
1&
0"
06
#1199
0$
#1200
0#
02
#1205
1#
12
#1208
b0 7
#1210
0#
02
#1215
1#
12
#1218
b11001 ,
1"
16
#1220
0#
02
#1225
1#
12
#1228
1$
#1230
0#
02
#1235
1#
12
#1238
b1 7
b11001 3
0&
#1240
0#
02
#1245
1#
12
#1248
1&
0"
06
#1249
0$
#1250
0#
02
#1255
1#
12
#1258
b0 7
#1260
0#
02
#1265
1#
12
#1268
b11010 ,
1"
16
#1270
0#
02
#1275
1#
12
#1278
1$
#1280
0#
02
#1285
1#
12
#1288
b1 7
b11010 3
0&
#1290
0#
02
#1295
1#
12
#1298
1&
0"
06
#1299
0$
#1300
0#
02
#1305
1#
12
#1308
b0 7
#1310
0#
02
#1315
1#
12
#1318
b11011 ,
1"
16
#1320
0#
02
#1325
1#
12
#1328
1$
#1330
0#
02
#1335
1#
12
#1338
b1 7
b11011 3
0&
#1340
0#
02
#1345
1#
12
#1348
1&
0"
06
#1349
0$
#1350
0#
02
#1355
1#
12
#1358
b0 7
#1360
0#
02
#1365
1#
12
#1368
b11100 ,
1"
16
#1370
0#
02
#1375
1#
12
#1378
1$
#1380
0#
02
#1385
1#
12
#1388
b1 7
b11100 3
0&
#1390
0#
02
#1395
1#
12
#1398
1&
0"
06
#1399
0$
#1400
0#
02
#1405
1#
12
#1408
b0 7
#1410
0#
02
#1415
1#
12
#1418
b11101 ,
1"
16
#1420
0#
02
#1425
1#
12
#1428
1$
#1430
0#
02
#1435
1#
12
#1438
b1 7
b11101 3
0&
#1440
0#
02
#1445
1#
12
#1448
1&
0"
06
#1449
0$
#1450
0#
02
#1455
1#
12
#1458
b0 7
#1460
0#
02
#1465
1#
12
#1468
0*
b11110 ,
1"
16
#1470
0#
02
#1475
1#
12
#1478
b11 7
1'
1$
#1480
0#
02
#1485
1#
12
#1488
0$
b100 7
b1010 5
0"
06
b1000000000 3
1&
#1490
0#
02
#1495
1#
12
#1498
b100000000 3
0!
08
b1001 5
#1500
0#
02
#1503
b0 -
b0 /
11
#1504
01
#1505
1#
12
#1508
b10000000 3
b1000 5
#1510
0#
02
#1513
b1 -
11
#1514
01
#1515
1#
12
#1518
b1000000 3
b111 5
#1520
0#
02
#1523
b10 -
11
#1524
01
#1525
1#
12
#1528
b100000 3
b110 5
#1530
0#
02
#1533
b11 -
11
#1534
01
#1535
1#
12
#1538
b10000 3
b101 5
#1540
0#
02
#1543
b100 -
11
#1544
01
#1545
1#
12
#1548
b1000 3
b100 5
#1550
0#
02
#1553
b101 -
11
#1554
01
#1555
1#
12
#1558
b100 3
b11 5
#1560
0#
02
#1563
b110 -
11
#1564
01
#1565
1#
12
#1568
b10 3
b10 5
#1570
0#
02
#1573
b111 -
11
#1574
01
#1575
1#
12
#1578
b1 3
b1 5
#1580
0#
02
#1583
b1000 -
11
#1584
01
#1585
1#
12
#1588
b1 7
b0 3
1!
18
b0 5
#1590
0#
02
#1593
b0 )
11
#1594
01
#1595
1#
12
#1598
b0 7
#1600
0#
02
#1605
1#
12
#1608
b0 ,
b11111 +
b11 7
1"
16
#1610
0#
02
#1615
1#
12
#1618
b100 7
b1010 5
0"
06
b1000000000 3
0'
1$
#1620
0#
02
#1625
1#
12
#1628
b100000000 3
0!
08
b1001 5
0&
#1630
0#
02
#1633
b0 -
11
#1634
01
#1635
1#
12
#1638
b10000000 3
b1000 5
#1640
0#
02
#1643
b1 -
11
#1644
01
#1645
1#
12
#1648
b1000000 3
b111 5
#1650
0#
02
#1653
b10 -
11
#1654
01
#1655
1#
12
#1658
b100000 3
b110 5
#1660
0#
02
#1663
b11 -
11
#1664
01
#1665
1#
12
#1668
b10000 3
b101 5
#1670
0#
02
#1673
b100 -
11
#1674
01
#1675
1#
12
#1678
b1000 3
b100 5
#1680
0#
02
#1683
b101 -
11
#1684
01
#1685
1#
12
#1688
b100 3
b11 5
#1690
0#
02
#1693
b110 -
11
#1694
01
#1695
1#
12
#1698
b10 3
b10 5
#1700
0#
02
#1703
b111 -
11
#1704
01
#1705
1#
12
#1708
b1 3
b1 5
#1710
0#
02
#1713
b1000 -
11
#1714
01
#1715
1#
12
#1718
b1 7
b0 3
1!
18
b0 5
#1720
0#
02
#1723
1(
b111111 )
11
#1724
0(
01
