es1.v
/*
    EPROM 2^8 x 4bit --> 8 fili di ind. 4 fili di dati
    64 segnali in gruppi di 4 celle consecutive --> ogni segnale sta in 4  celle
    es. 
        00000000 contiene V[0]
        00000001 contiene V[1]
        00000010 contiene T[0]
        00000011 contiene T[1]
*/

module ABC (
    reset_, clock, data,
    addr, s_, mr_, out 
);
    input reset_, clock;
    input [3:0] data;
    output s_, mr_;
    output [6:0] out;
    output[7:0] addr;

    reg[7:0] V;
    reg[7:0] T;
    reg[6:0] COUNT;
    reg[2:0] OUT; assign out = OUT;
    reg S; assign s_ = S;
    reg MR; assign mr_ = MR;
    reg[7:0] ADDR; assign addr = ADDR;

    wire [6:0] Tc, Vc;
    CONV convV(
        .c1(V[3:0]), .c2(V[7:4]),
        .converted(Vc)
    );
    CONV convT(
        .c1(T[3:0]), .c2(T[7:4]),
        .converted(Tc)
    );

    reg[2:0] STAR; parameter S0=0, S1=1, S2=2, S3=3, S4=4;

    always @(reset_==0) #1
        begin
            COUNT <= 99;
            OUT <= 0;
            STAR <= S0;
            ADDR <= 0;
        end
    always @(posedge clock) if(reset_==1) #3
        casex(STAR)
            S0:
                begin
                    MR <= 0;
                    S <= 0;
                    COUNT <= COUNT-1;
                    ADDR <= ADDR + 1;
                    V[3:0] <= data;
                    STAR <= S1;
                end
            S1:
                begin
                    COUNT <= COUNT-1;
                    ADDR <= ADDR + 1;
                    V[7:4] <= data;
                    STAR <= S2;
                end
            S2:
                begin
                    COUNT <= COUNT-1;
                    ADDR <= ADDR + 1;
                    T[3:0] <= data;
                    STAR <= S3;
                end
            S3:
                begin
                    COUNT <= COUNT-1;
                    ADDR <= ADDR + 1;
                    T[7:4] <= data;
                    MR <= 1;
                    S <= 1;
                    STAR <= (COUNT==1)? S4 : S3;
                end
            S4:
                begin
                    OUT <= Vc;
                    COUNT <= Tc;
                    STAR <= S0;
                end
        endcase
endmodule

module CONV (
    c1, c2,
    converted
);
    input [3:0] c1, c2;
    output [6:0] converted;

    wire [7:0] m1, m2;
    mul_add_nat moltiplicatore(
        .x(c2), .y(4'B1010), .c(),
        .m(m1)
    );
    add Sommatore(
        .x(m1), .y({4'B1010, c2}), .c_in(),
        .s(m2), .c_out(), .ow()
    );
    assign converted = m2[6:0];
endmodule

testbench1.v
module testbench();

    wire clock;

    clock_generator clk(
        .clock(clock)
    );

    wire [7:0] addr;
    wire [3:0] data;
    wire s_, mr_;

    eprom_256x4 eprom(
        .addr(addr), .s_(s_), .mr_(mr_),
        .data(data)
    );

    reg reset_;
    wire [6:0] out;
    
    ABC dut (
        .data(data), .reset_(reset_), .clock(clock),
        .out(out), .addr(addr), .s_(s_), .mr_(mr_)
    );

    // simulation variables
    realtime prev_sample;
    realtime current_sample;
    realtime diff;

    integer i;
    reg [6:0] v;
    reg [6:0] t;

    initial
        begin
            $dumpfile("waveform.vcd");
            $dumpvars;

            //the following structure is used to wait for expected signals, and fail if too much time passes
            fork : f
                begin
                    #100000;
                    $display("Timeout - waiting for signal failed");
                    disable f;
                end
            //actual tests start here
                begin
                    //reset phase
                    reset_ = 0; #(clk.HALF_PERIOD);
                    
                    //first posedge. as reset_ is set to 1, ABC starts the cycle from V_i = 0, T_i = 99
                    reset_ = 1;
                    
                    prev_sample = $realtime;

                    #(clk.HALF_PERIOD);
                    //clock is at negative edge

                    if(out !== 0)
                        $display("out is not 0 after reset");

                    @(out);
                    prev_sample = current_sample;
                    current_sample = $realtime;
                    diff = (current_sample - prev_sample)/(2*clk.HALF_PERIOD);
                    if(diff < 98 || diff > 99)    // need some leeway around reset
                        $display("reset-cycle of 99 failed: %g", diff);

                    for(i = 0; i < 64; i++)
                        begin
                            // compute next v and t, according to relation used in test eprom
                            v = ((i + 1) %10) * 10 + ((i + 1) % 10);
                            t = ((i % 9) + 1) * 10 + (i % 10);

                            if(out !== v)
                                $display("%g-th out is not %g, %g instead", i, v, out);

                            @(out)  //wait for next value change
                            prev_sample = current_sample;
                            current_sample = $realtime;
                            diff = (current_sample - prev_sample)/(2*clk.HALF_PERIOD);
                            if(diff != t)    // need some leeway around reset
                                $display("%g-th value was not held for %g cycles, %g instead", i, t, diff);
                        end

                    

                    disable f;
                end   
            join

            $finish;
        end

endmodule

// il modulo eprom_256x4 simula una eprom con una funzione nota tra ingresso e uscita
// tale funzione è usata per verificare il comportamento della rete potendo calcolare a priori cosa dovrebbe fare 
module eprom_256x4 (
    addr, s_, mr_,
    data
);
    input [7:0] addr;
    input s_, mr_;

    output [3:0] data;

    wire [5:0] i; 
    wire [1:0] offset;
    
    assign i = addr[7:2];
    assign offset = addr[1:0];  

    assign #1 data = ((s_ !== 0) || (mr_ !== 0)) ? 4'Bz : f(i, offset);

    function [3:0] f;
        input [5:0] i; 
        input [1:0] offset;
         
        casex(offset)
            0: f = (i + 1) % 10;    // V_i_0
            1: f = (i + 1) % 10;    // V_i_1
            2: f = i % 10;          // T_i_0
            3: f = (i % 9) + 1;     // T_i_1
        endcase
    endfunction

endmodule

// generatore del segnale di clock
module clock_generator(
    clock
);
    output clock;

    parameter HALF_PERIOD = 5;

    reg CLOCK;
    assign clock = CLOCK;

    initial CLOCK <= 0;
    always #HALF_PERIOD CLOCK <= ~CLOCK;

endmodule

reti_standard.v
// Sommatore valido sia per naturali che per interi, in base 2.
// Sia input che output sono a N cifre.
// Il circuito ha in uscita sia il carry che l'overflow, sta all'utilizzatore collegare quello corretto.
module add( 
    x, y, c_in,
    s, c_out, ow    
);
    parameter N = 8;

    input [N-1:0] x, y;
    input c_in;

    output [N-1:0] s;
    output c_out, ow;

    assign #1 {c_out, s} = x + y + c_in;
    assign #1 ow = (x[N-1] == y[N-1]) && (x[N-1] != s[N-1]);

endmodule

// Moltiplicatore con addizionatore per naturali in base 2.
// Moltiplicando (x) e addendo (c) a N bit, moltiplicatore (y) a M bit.
// Risultato (m) su N+M bit
module mul_add_nat(
    x, y, c,
    m
);

    parameter N = 4;
    parameter M = 4;

    input [N-1:0] x, c;
    input [M-1:0] y;

    output [N+M-1:0] m;

    assign #1 m = (x * y) + c;

endmodule

// Comparatore per naturali in base 2.
// Ingressi a N bit.
// Il flag min vale 1 se a < b
// Il flag eq vale 1 se a == b
module comp_nat(
    a, b,
    min, eq 
);

    parameter N = 2;

    input [N-1:0] a, b;
    output min, eq;

    assign min = (a < b);
    assign eq = (a == b);

endmodule

esercitazione2020/waveform.vcd
$date
	Wed May 19 16:23:07 2021
$end
$version
	Icarus Verilog
$end
$timescale
	1s
$end
$scope module comp_nat $end
$var wire 2 ! a [1:0] $end
$var wire 2 " b [1:0] $end
$var wire 1 # min $end
$var wire 1 $ eq $end
$upscope $end
$scope module testbench $end
$var wire 1 % s_ $end
$var wire 7 & out [6:0] $end
$var wire 1 ' mr_ $end
$var wire 4 ( data [3:0] $end
$var wire 1 ) clock $end
$var wire 8 * addr [7:0] $end
$var reg 1 + reset_ $end
$var reg 7 , t [6:0] $end
$var reg 7 - v [6:0] $end
$var real 1 . current_sample $end
$var real 1 / diff $end
$var integer 32 0 i [31:0] $end
$var real 1 1 prev_sample $end
$scope module clk $end
$var wire 1 ) clock $end
$var reg 1 2 CLOCK $end
$upscope $end
$scope module dut $end
$var wire 8 3 addr [7:0] $end
$var wire 1 ) clock $end
$var wire 1 ' mr_ $end
$var wire 1 + reset_ $end
$var wire 1 % s_ $end
$var wire 7 4 out [6:0] $end
$var wire 4 5 data [3:0] $end
$var wire 7 6 Vc [6:0] $end
$var wire 7 7 Tc [6:0] $end
$var reg 8 8 ADDR [7:0] $end
$var reg 7 9 COUNT [6:0] $end
$var reg 1 ' MR $end
$var reg 3 : OUT [2:0] $end
$var reg 1 % S $end
$var reg 3 ; STAR [2:0] $end
$var reg 8 < T [7:0] $end
$var reg 8 = V [7:0] $end
$scope module convT $end
$var wire 4 > c1 [3:0] $end
$var wire 4 ? c2 [3:0] $end
$var wire 8 @ m2 [7:0] $end
$var wire 8 A m1 [7:0] $end
$var wire 7 B converted [6:0] $end
$scope module Sommatore $end
$var wire 1 C c_in $end
$var wire 1 D ow $end
$var wire 8 E y [7:0] $end
$var wire 8 F x [7:0] $end
$var wire 8 G s [7:0] $end
$var wire 1 H c_out $end
$upscope $end
$scope module moltiplicatore $end
$var wire 4 I c [3:0] $end
$var wire 4 J x [3:0] $end
$var wire 4 K y [3:0] $end
$var wire 8 L m [7:0] $end
$upscope $end
$upscope $end
$scope module convV $end
$var wire 4 M c1 [3:0] $end
$var wire 4 N c2 [3:0] $end
$var wire 8 O m2 [7:0] $end
$var wire 8 P m1 [7:0] $end
$var wire 7 Q converted [6:0] $end
$scope module Sommatore $end
$var wire 1 R c_in $end
$var wire 1 S ow $end
$var wire 8 T y [7:0] $end
$var wire 8 U x [7:0] $end
$var wire 8 V s [7:0] $end
$var wire 1 W c_out $end
$upscope $end
$scope module moltiplicatore $end
$var wire 4 X c [3:0] $end
$var wire 4 Y x [3:0] $end
$var wire 4 Z y [3:0] $end
$var wire 8 [ m [7:0] $end
$upscope $end
$upscope $end
$upscope $end
$scope module eprom $end
$var wire 8 \ addr [7:0] $end
$var wire 1 ' mr_ $end
$var wire 1 % s_ $end
$var wire 2 ] offset [1:0] $end
$var wire 6 ^ i [5:0] $end
$var wire 4 _ data [3:0] $end
$scope function f $end
$var reg 4 ` f [3:0] $end
$var reg 6 a i [5:0] $end
$var reg 2 b offset [1:0] $end
$upscope $end
$upscope $end
$scope fork f $end
$upscope $end
$upscope $end
$enddefinitions $end
#0
$dumpvars
bx b
bx a
bx `
bx _
bx ^
bx ]
bx \
bx [
b1010 Z
bx Y
bz X
xW
bx V
bx U
b1010xxxx T
xS
zR
bx Q
bx P
bx O
bx N
bx M
bx L
b1010 K
bx J
bz I
xH
bx G
bx F
b1010xxxx E
xD
zC
bx B
bx A
bx @
bx ?
bx >
bx =
bx <
bx ;
bx :
bx 9
bx 8
bx 7
bx 6
bx 5
b0xxx 4
bx 3
02
r0 1
bx 0
r0 /
r0 .
bx -
bx ,
0+
bx *
0)
bx (
x'
b0xxx &
x%
x$
x#
bz "
bz !
$end
#1
b1 `
b0 b
b0 a
b0 ^
b0 ]
b0 *
b0 3
b0 8
b0 \
b0 ;
b0 &
b0 4
b0 :
b1100011 9
bz (
bz 5
bz _
#5
1)
12
r5 1
1+
#8
b1 b
bz M
b1 ]
b1 ;
bxzzzz =
b1 *
b1 3
b1 8
b1 \
b1100010 9
0%
0'
#9
b1 (
b1 5
b1 _
#10
0)
02
#15
1)
12
#18
b0 `
b10 b
b10100001 T
b1 N
b1 Y
b10 ]
b10 ;
b1zzzz =
b10 *
b10 3
b10 8
b10 \
b1100001 9
#19
b0 (
b0 5
b0 _
#20
0)
02
#25
1)
12
#28
b1 `
b11 b
b0 >
b11 ]
b11 ;
bx0000 <
b11 *
b11 3
b11 8
b11 \
b1100000 9
#29
b1 (
b1 5
b1 _
#30
0)
02
#35
1)
12
#38
b10 `
b0 b
b1 a
b10100001 E
b1 ?
b1 J
b1 ^
b0 ]
1%
1'
b10000 <
b100 *
b100 3
b100 8
b100 \
b1011111 9
#39
bz (
bz 5
bz _
#40
0)
02
#45
1)
12
#48
b1 b
b1010zzzz E
bz ?
bz J
b1 ]
bz0000 <
b101 *
b101 3
b101 8
b101 \
b1011110 9
#50
0)
02
#55
1)
12
#58
b1 `
b10 b
b10 ]
b110 *
b110 3
b110 8
b110 \
b1011101 9
#60
0)
02
#65
1)
12
#68
b10 `
b11 b
b11 ]
b111 *
b111 3
b111 8
b111 \
b1011100 9
#70
0)
02
#75
1)
12
#78
b11 `
b0 b
b10 a
b10 ^
b0 ]
b1000 *
b1000 3
b1000 8
b1000 \
b1011011 9
#80
0)
02
#85
1)
12
#88
b1 b
b1 ]
b1001 *
b1001 3
b1001 8
b1001 \
b1011010 9
#90
0)
02
#95
1)
12
#98
b10 `
b10 b
b10 ]
b1010 *
b1010 3
b1010 8
b1010 \
b1011001 9
#100
0)
02
#105
1)
12
#108
b11 `
b11 b
b11 ]
b1011 *
b1011 3
b1011 8
b1011 \
b1011000 9
#110
0)
02
#115
1)
12
#118
b100 `
b0 b
b11 a
b11 ^
b0 ]
b1100 *
b1100 3
b1100 8
b1100 \
b1010111 9
#120
0)
02
#125
1)
12
#128
b1 b
b1 ]
b1101 *
b1101 3
b1101 8
b1101 \
b1010110 9
#130
0)
02
#135
1)
12
#138
b11 `
b10 b
b10 ]
b1110 *
b1110 3
b1110 8
b1110 \
b1010101 9
#140
0)
02
#145
1)
12
#148
b100 `
b11 b
b11 ]
b1111 *
b1111 3
b1111 8
b1111 \
b1010100 9
#150
0)
02
#155
1)
12
#158
b101 `
b0 b
b100 a
b100 ^
b0 ]
b10000 *
b10000 3
b10000 8
b10000 \
b1010011 9
#160
0)
02
#165
1)
12
#168
b1 b
b1 ]
b10001 *
b10001 3
b10001 8
b10001 \
b1010010 9
#170
0)
02
#175
1)
12
#178
b100 `
b10 b
b10 ]
b10010 *
b10010 3
b10010 8
b10010 \
b1010001 9
#180
0)
02
#185
1)
12
#188
b101 `
b11 b
b11 ]
b10011 *
b10011 3
b10011 8
b10011 \
b1010000 9
#190
0)
02
#195
1)
12
#198
b110 `
b0 b
b101 a
b101 ^
b0 ]
b10100 *
b10100 3
b10100 8
b10100 \
b1001111 9
#200
0)
02
#205
1)
12
#208
b1 b
b1 ]
b10101 *
b10101 3
b10101 8
b10101 \
b1001110 9
#210
0)
02
#215
1)
12
#218
b101 `
b10 b
b10 ]
b10110 *
b10110 3
b10110 8
b10110 \
b1001101 9
#220
0)
02
#225
1)
12
#228
b110 `
b11 b
b11 ]
b10111 *
b10111 3
b10111 8
b10111 \
b1001100 9
#230
0)
02
#235
1)
12
#238
b111 `
b0 b
b110 a
b110 ^
b0 ]
b11000 *
b11000 3
b11000 8
b11000 \
b1001011 9
#240
0)
02
#245
1)
12
#248
b1 b
b1 ]
b11001 *
b11001 3
b11001 8
b11001 \
b1001010 9
#250
0)
02
#255
1)
12
#258
b110 `
b10 b
b10 ]
b11010 *
b11010 3
b11010 8
b11010 \
b1001001 9
#260
0)
02
#265
1)
12
#268
b111 `
b11 b
b11 ]
b11011 *
b11011 3
b11011 8
b11011 \
b1001000 9
#270
0)
02
#275
1)
12
#278
b1000 `
b0 b
b111 a
b111 ^
b0 ]
b11100 *
b11100 3
b11100 8
b11100 \
b1000111 9
#280
0)
02
#285
1)
12
#288
b1 b
b1 ]
b11101 *
b11101 3
b11101 8
b11101 \
b1000110 9
#290
0)
02
#295
1)
12
#298
b111 `
b10 b
b10 ]
b11110 *
b11110 3
b11110 8
b11110 \
b1000101 9
#300
0)
02
#305
1)
12
#308
b1000 `
b11 b
b11 ]
b11111 *
b11111 3
b11111 8
b11111 \
b1000100 9
#310
0)
02
#315
1)
12
#318
b1001 `
b0 b
b1000 a
b1000 ^
b0 ]
b100000 *
b100000 3
b100000 8
b100000 \
b1000011 9
#320
0)
02
#325
1)
12
#328
b1 b
b1 ]
b100001 *
b100001 3
b100001 8
b100001 \
b1000010 9
#330
0)
02
#335
1)
12
#338
b1000 `
b10 b
b10 ]
b100010 *
b100010 3
b100010 8
b100010 \
b1000001 9
#340
0)
02
#345
1)
12
#348
b1001 `
b11 b
b11 ]
b100011 *
b100011 3
b100011 8
b100011 \
b1000000 9
#350
0)
02
#355
1)
12
#358
b0 `
b0 b
b1001 a
b1001 ^
b0 ]
b100100 *
b100100 3
b100100 8
b100100 \
b111111 9
#360
0)
02
#365
1)
12
#368
b1 b
b1 ]
b100101 *
b100101 3
b100101 8
b100101 \
b111110 9
#370
0)
02
#375
1)
12
#378
b1001 `
b10 b
b10 ]
b100110 *
b100110 3
b100110 8
b100110 \
b111101 9
#380
0)
02
#385
1)
12
#388
b1 `
b11 b
b11 ]
b100111 *
b100111 3
b100111 8
b100111 \
b111100 9
#390
0)
02
#395
1)
12
#398
b0 b
b1010 a
b1010 ^
b0 ]
b101000 *
b101000 3
b101000 8
b101000 \
b111011 9
#400
0)
02
#405
1)
12
#408
b1 b
b1 ]
b101001 *
b101001 3
b101001 8
b101001 \
b111010 9
#410
0)
02
#415
1)
12
#418
b0 `
b10 b
b10 ]
b101010 *
b101010 3
b101010 8
b101010 \
b111001 9
#420
0)
02
#425
1)
12
#428
b10 `
b11 b
b11 ]
b101011 *
b101011 3
b101011 8
b101011 \
b111000 9
#430
0)
02
#435
1)
12
#438
b0 b
b1011 a
b1011 ^
b0 ]
b101100 *
b101100 3
b101100 8
b101100 \
b110111 9
#440
0)
02
#445
1)
12
#448
b1 b
b1 ]
b101101 *
b101101 3
b101101 8
b101101 \
b110110 9
#450
0)
02
#455
1)
12
#458
b1 `
b10 b
b10 ]
b101110 *
b101110 3
b101110 8
b101110 \
b110101 9
#460
0)
02
#465
1)
12
#468
b11 `
b11 b
b11 ]
b101111 *
b101111 3
b101111 8
b101111 \
b110100 9
#470
0)
02
#475
1)
12
#478
b0 b
b1100 a
b1100 ^
b0 ]
b110000 *
b110000 3
b110000 8
b110000 \
b110011 9
#480
0)
02
#485
1)
12
#488
b1 b
b1 ]
b110001 *
b110001 3
b110001 8
b110001 \
b110010 9
#490
0)
02
#495
1)
12
#498
b10 `
b10 b
b10 ]
b110010 *
b110010 3
b110010 8
b110010 \
b110001 9
#500
0)
02
#505
1)
12
#508
b100 `
b11 b
b11 ]
b110011 *
b110011 3
b110011 8
b110011 \
b110000 9
#510
0)
02
#515
1)
12
#518
b0 b
b1101 a
b1101 ^
b0 ]
b110100 *
b110100 3
b110100 8
b110100 \
b101111 9
#520
0)
02
#525
1)
12
#528
b1 b
b1 ]
b110101 *
b110101 3
b110101 8
b110101 \
b101110 9
#530
0)
02
#535
1)
12
#538
b11 `
b10 b
b10 ]
b110110 *
b110110 3
b110110 8
b110110 \
b101101 9
#540
0)
02
#545
1)
12
#548
b101 `
b11 b
b11 ]
b110111 *
b110111 3
b110111 8
b110111 \
b101100 9
#550
0)
02
#555
1)
12
#558
b0 b
b1110 a
b1110 ^
b0 ]
b111000 *
b111000 3
b111000 8
b111000 \
b101011 9
#560
0)
02
#565
1)
12
#568
b1 b
b1 ]
b111001 *
b111001 3
b111001 8
b111001 \
b101010 9
#570
0)
02
#575
1)
12
#578
b100 `
b10 b
b10 ]
b111010 *
b111010 3
b111010 8
b111010 \
b101001 9
#580
0)
02
#585
1)
12
#588
b110 `
b11 b
b11 ]
b111011 *
b111011 3
b111011 8
b111011 \
b101000 9
#590
0)
02
#595
1)
12
#598
b0 b
b1111 a
b1111 ^
b0 ]
b111100 *
b111100 3
b111100 8
b111100 \
b100111 9
#600
0)
02
#605
1)
12
#608
b1 b
b1 ]
b111101 *
b111101 3
b111101 8
b111101 \
b100110 9
#610
0)
02
#615
1)
12
#618
b101 `
b10 b
b10 ]
b111110 *
b111110 3
b111110 8
b111110 \
b100101 9
#620
0)
02
#625
1)
12
#628
b111 `
b11 b
b11 ]
b111111 *
b111111 3
b111111 8
b111111 \
b100100 9
#630
0)
02
#635
1)
12
#638
b0 b
b10000 a
b10000 ^
b0 ]
b1000000 *
b1000000 3
b1000000 8
b1000000 \
b100011 9
#640
0)
02
#645
1)
12
#648
b1 b
b1 ]
b1000001 *
b1000001 3
b1000001 8
b1000001 \
b100010 9
#650
0)
02
#655
1)
12
#658
b110 `
b10 b
b10 ]
b1000010 *
b1000010 3
b1000010 8
b1000010 \
b100001 9
#660
0)
02
#665
1)
12
#668
b1000 `
b11 b
b11 ]
b1000011 *
b1000011 3
b1000011 8
b1000011 \
b100000 9
#670
0)
02
#675
1)
12
#678
b0 b
b10001 a
b10001 ^
b0 ]
b1000100 *
b1000100 3
b1000100 8
b1000100 \
b11111 9
#680
0)
02
#685
1)
12
#688
b1 b
b1 ]
b1000101 *
b1000101 3
b1000101 8
b1000101 \
b11110 9
#690
0)
02
#695
1)
12
#698
b111 `
b10 b
b10 ]
b1000110 *
b1000110 3
b1000110 8
b1000110 \
b11101 9
#700
0)
02
#705
1)
12
#708
b1001 `
b11 b
b11 ]
b1000111 *
b1000111 3
b1000111 8
b1000111 \
b11100 9
#710
0)
02
#715
1)
12
#718
b0 b
b10010 a
b10010 ^
b0 ]
b1001000 *
b1001000 3
b1001000 8
b1001000 \
b11011 9
#720
0)
02
#725
1)
12
#728
b1 b
b1 ]
b1001001 *
b1001001 3
b1001001 8
b1001001 \
b11010 9
#730
0)
02
#735
1)
12
#738
b1000 `
b10 b
b10 ]
b1001010 *
b1001010 3
b1001010 8
b1001010 \
b11001 9
#740
0)
02
#745
1)
12
#748
b1 `
b11 b
b11 ]
b1001011 *
b1001011 3
b1001011 8
b1001011 \
b11000 9
#750
0)
02
#755
1)
12
#758
b0 `
b0 b
b10011 a
b10011 ^
b0 ]
b1001100 *
b1001100 3
b1001100 8
b1001100 \
b10111 9
#760
0)
02
#765
1)
12
#768
b1 b
b1 ]
b1001101 *
b1001101 3
b1001101 8
b1001101 \
b10110 9
#770
0)
02
#775
1)
12
#778
b1001 `
b10 b
b10 ]
b1001110 *
b1001110 3
b1001110 8
b1001110 \
b10101 9
#780
0)
02
#785
1)
12
#788
b10 `
b11 b
b11 ]
b1001111 *
b1001111 3
b1001111 8
b1001111 \
b10100 9
#790
0)
02
#795
1)
12
#798
b1 `
b0 b
b10100 a
b10100 ^
b0 ]
b1010000 *
b1010000 3
b1010000 8
b1010000 \
b10011 9
#800
0)
02
#805
1)
12
#808
b1 b
b1 ]
b1010001 *
b1010001 3
b1010001 8
b1010001 \
b10010 9
#810
0)
02
#815
1)
12
#818
b0 `
b10 b
b10 ]
b1010010 *
b1010010 3
b1010010 8
b1010010 \
b10001 9
#820
0)
02
#825
1)
12
#828
b11 `
b11 b
b11 ]
b1010011 *
b1010011 3
b1010011 8
b1010011 \
b10000 9
#830
0)
02
#835
1)
12
#838
b10 `
b0 b
b10101 a
b10101 ^
b0 ]
b1010100 *
b1010100 3
b1010100 8
b1010100 \
b1111 9
#840
0)
02
#845
1)
12
#848
b1 b
b1 ]
b1010101 *
b1010101 3
b1010101 8
b1010101 \
b1110 9
#850
0)
02
#855
1)
12
#858
b1 `
b10 b
b10 ]
b1010110 *
b1010110 3
b1010110 8
b1010110 \
b1101 9
#860
0)
02
#865
1)
12
#868
b100 `
b11 b
b11 ]
b1010111 *
b1010111 3
b1010111 8
b1010111 \
b1100 9
#870
0)
02
#875
1)
12
#878
b11 `
b0 b
b10110 a
b10110 ^
b0 ]
b1011000 *
b1011000 3
b1011000 8
b1011000 \
b1011 9
#880
0)
02
#885
1)
12
#888
b1 b
b1 ]
b1011001 *
b1011001 3
b1011001 8
b1011001 \
b1010 9
#890
0)
02
#895
1)
12
#898
b10 `
b10 b
b10 ]
b1011010 *
b1011010 3
b1011010 8
b1011010 \
b1001 9
#900
0)
02
#905
1)
12
#908
b101 `
b11 b
b11 ]
b1011011 *
b1011011 3
b1011011 8
b1011011 \
b1000 9
#910
0)
02
#915
1)
12
#918
b100 `
b0 b
b10111 a
b10111 ^
b0 ]
b1011100 *
b1011100 3
b1011100 8
b1011100 \
b111 9
#920
0)
02
#925
1)
12
#928
b1 b
b1 ]
b1011101 *
b1011101 3
b1011101 8
b1011101 \
b110 9
#930
0)
02
#935
1)
12
#938
b11 `
b10 b
b10 ]
b1011110 *
b1011110 3
b1011110 8
b1011110 \
b101 9
#940
0)
02
#945
1)
12
#948
b110 `
b11 b
b11 ]
b1011111 *
b1011111 3
b1011111 8
b1011111 \
b100 9
#950
0)
02
#955
1)
12
#958
b101 `
b0 b
b11000 a
b11000 ^
b0 ]
b1100000 *
b1100000 3
b1100000 8
b1100000 \
b11 9
#960
0)
02
#965
1)
12
#968
b1 b
b1 ]
b1100001 *
b1100001 3
b1100001 8
b1100001 \
b10 9
#970
0)
02
#975
1)
12
#978
b100 `
b10 b
b10 ]
b1100010 *
b1100010 3
b1100010 8
b1100010 \
b1 9
#980
0)
02
#985
1)
12
#988
b111 `
b11 b
b11 ]
b100 ;
b1100011 *
b1100011 3
b1100011 8
b1100011 \
b0 9
#990
0)
02
#995
1)
12
#998
b1010 ,
b1011 -
b0 0
r99.8 /
r998 .
r0 1
b0 ;
bx 9
b0xxx &
b0xxx 4
bx :
#1000
0)
02
#1005
1)
12
#1008
b110 `
b0 b
b11001 a
b11001 ^
b0 ]
b1 ;
b1100100 *
b1100100 3
b1100100 8
b1100100 \
0%
0'
#1009
b110 (
b110 5
b110 _
#1010
0)
02
#1015
1)
12
#1018
b1 b
b10100110 T
b110 N
b110 Y
b1 ]
b10 ;
b110zzzz =
b1100101 *
b1100101 3
b1100101 8
b1100101 \
#1020
0)
02
#1025
1)
12
#1028
b101 `
b10 b
b110 >
b10 ]
b11 ;
bz0110 <
b1100110 *
b1100110 3
b1100110 8
b1100110 \
#1029
b101 (
b101 5
b101 _
#1030
0)
02
#1035
1)
12
#1038
b1000 `
b11 b
b10100101 E
b101 ?
b101 J
b11 ]
bx ;
1%
1'
b1010110 <
b1100111 *
b1100111 3
b1100111 8
b1100111 \
#1039
bz (
bz 5
bz _
#1040
0)
02
#1045
1)
12
#1048
b111 `
b0 b
b11010 a
b11010 ^
b0 ]
b1 ;
b1101000 *
b1101000 3
b1101000 8
b1101000 \
0%
0'
#1049
b111 (
b111 5
b111 _
#1050
0)
02
#1055
1)
12
#1058
b1 b
b10100111 T
b111 N
b111 Y
b1 ]
b10 ;
b111zzzz =
b1101001 *
b1101001 3
b1101001 8
b1101001 \
#1060
0)
02
#1065
1)
12
#1068
b110 `
b10 b
b111 >
b10 ]
b11 ;
b1010111 <
b1101010 *
b1101010 3
b1101010 8
b1101010 \
#1069
b110 (
b110 5
b110 _
#1070
0)
02
#1075
1)
12
#1078
b1001 `
b11 b
b10100110 E
b110 ?
b110 J
b11 ]
bx ;
1%
1'
b1100111 <
b1101011 *
b1101011 3
b1101011 8
b1101011 \
#1079
bz (
bz 5
bz _
#1080
0)
02
#1085
1)
12
#1088
b1000 `
b0 b
b11011 a
b11011 ^
b0 ]
b1 ;
b1101100 *
b1101100 3
b1101100 8
b1101100 \
0%
0'
#1089
b1000 (
b1000 5
b1000 _
#1090
0)
02
#1095
1)
12
#1098
b1 b
b10101000 T
b1000 N
b1000 Y
b1 ]
b10 ;
b1000zzzz =
b1101101 *
b1101101 3
b1101101 8
b1101101 \
#1100
0)
02
#1105
1)
12
#1108
b111 `
b10 b
b1000 >
b10 ]
b11 ;
b1101000 <
b1101110 *
b1101110 3
b1101110 8
b1101110 \
#1109
b111 (
b111 5
b111 _
#1110
0)
02
#1115
1)
12
#1118
b1 `
b11 b
b10100111 E
b111 ?
b111 J
b11 ]
bx ;
1%
1'
b1111000 <
b1101111 *
b1101111 3
b1101111 8
b1101111 \
#1119
bz (
bz 5
bz _
#1120
0)
02
#1125
1)
12
#1128
b1001 `
b0 b
b11100 a
b11100 ^
b0 ]
b1 ;
b1110000 *
b1110000 3
b1110000 8
b1110000 \
0%
0'
#1129
b1001 (
b1001 5
b1001 _
#1130
0)
02
#1135
1)
12
#1138
b1 b
b10101001 T
b1001 N
b1001 Y
b1 ]
b10 ;
b1001zzzz =
b1110001 *
b1110001 3
b1110001 8
b1110001 \
#1140
0)
02
#1145
1)
12
#1148
b1000 `
b10 b
b1001 >
b10 ]
b11 ;
b1111001 <
b1110010 *
b1110010 3
b1110010 8
b1110010 \
#1149
b1000 (
b1000 5
b1000 _
#1150
0)
02
#1155
1)
12
#1158
b10 `
b11 b
b10101000 E
b1000 ?
b1000 J
b11 ]
bx ;
1%
1'
b10001001 <
b1110011 *
b1110011 3
b1110011 8
b1110011 \
#1159
bz (
bz 5
bz _
#1160
0)
02
#1165
1)
12
#1168
b0 `
b0 b
b11101 a
b11101 ^
b0 ]
b1 ;
b1110100 *
b1110100 3
b1110100 8
b1110100 \
0%
0'
#1169
b0 (
b0 5
b0 _
#1170
0)
02
#1175
1)
12
#1178
b1 b
b10100000 T
b0 N
b0 Y
b1 ]
b10 ;
b0zzzz =
b1110101 *
b1110101 3
b1110101 8
b1110101 \
#1180
0)
02
#1185
1)
12
#1188
b1001 `
b10 b
b0 >
b10 ]
b11 ;
b10000000 <
b1110110 *
b1110110 3
b1110110 8
b1110110 \
#1189
b1001 (
b1001 5
b1001 _
#1190
0)
02
#1195
1)
12
#1198
b11 `
b11 b
b10101001 E
b1001 ?
b1001 J
b11 ]
bx ;
1%
1'
b10010000 <
b1110111 *
b1110111 3
b1110111 8
b1110111 \
#1199
bz (
bz 5
bz _
#1200
0)
02
#1205
1)
12
#1208
b1 `
b0 b
b11110 a
b11110 ^
b0 ]
b1 ;
b1111000 *
b1111000 3
b1111000 8
b1111000 \
0%
0'
#1209
b1 (
b1 5
b1 _
#1210
0)
02
#1215
1)
12
#1218
b1 b
b10100001 T
b1 N
b1 Y
b1 ]
b10 ;
b1zzzz =
b1111001 *
b1111001 3
b1111001 8
b1111001 \
#1220
0)
02
#1225
1)
12
#1228
b0 `
b10 b
b1 >
b10 ]
b11 ;
b10010001 <
b1111010 *
b1111010 3
b1111010 8
b1111010 \
#1229
b0 (
b0 5
b0 _
#1230
0)
02
#1235
1)
12
#1238
b100 `
b11 b
b10100000 E
b0 ?
b0 J
b11 ]
bx ;
1%
1'
b1 <
b1111011 *
b1111011 3
b1111011 8
b1111011 \
#1239
bz (
bz 5
bz _
#1240
0)
02
#1245
1)
12
#1248
b10 `
b0 b
b11111 a
b11111 ^
b0 ]
b1 ;
b1111100 *
b1111100 3
b1111100 8
b1111100 \
0%
0'
#1249
b10 (
b10 5
b10 _
#1250
0)
02
#1255
1)
12
#1258
b1 b
b10100010 T
b10 N
b10 Y
b1 ]
b10 ;
b10zzzz =
b1111101 *
b1111101 3
b1111101 8
b1111101 \
#1260
0)
02
#1265
1)
12
